xylog/__init__.py
xylog/log.py
xylog-0.0.3.dist-info/METADATA
xylog-0.0.3.dist-info/WHEEL
xylog-0.0.3.dist-info/top_level.txt
xylog-0.0.3.dist-info/RECORD
